tinned_python/__init__.py
tinned_python/cli.py
tinned_python/tinned_python.py
tinned_python-0.1.2.dist-info/AUTHORS.rst
tinned_python-0.1.2.dist-info/LICENSE
tinned_python-0.1.2.dist-info/METADATA
tinned_python-0.1.2.dist-info/WHEEL
tinned_python-0.1.2.dist-info/entry_points.txt
tinned_python-0.1.2.dist-info/top_level.txt
tinned_python-0.1.2.dist-info/RECORD
