Metadata-Version: 2.1
Name: tinned-python
Version: 0.1.2
Summary: Python data, in a tin
Home-page: https://github.com/tmfnll/tinned_python
Author: Tom Finill
Author-email: tomfinill@gmail.com
License: MIT license
Keywords: tinned_python
Platform: UNKNOWN
Classifier: Development Status :: 2 - Pre-Alpha
Classifier: Intended Audience :: Developers
Classifier: License :: OSI Approved :: MIT License
Classifier: Natural Language :: English
Classifier: Programming Language :: Python :: 3
Classifier: Programming Language :: Python :: 3.5
Classifier: Programming Language :: Python :: 3.6
Classifier: Programming Language :: Python :: 3.7
Classifier: Programming Language :: Python :: 3.8
Requires-Python: >=3.5
Requires-Dist: Click (>=7.0)
